<annotation>
	<folder>images</folder>
	<filename>2011_000264.xml</filename>
	<path>Datasets_mine/labeled/head_voc\labels/2011_000264.xml</path>
	<source>
		<database>Unknown</database>
	</source>
	<size>
		<width>500</width>
		<height>375</height>
		<depth>3</depth>
	</size>
	<segmented>0</segmented>
	<object>
		<name>head</name>
		<pose>Unspecified</pose>
		<truncated>0</truncated>
		<difficult>0</difficult>
		<bndbox>
			<xmin>253</xmin>
			<ymin>43</ymin>
			<xmax>307</xmax>
			<ymax>112</ymax>
		</bndbox>
	</object>
	
</annotation>	